plugin.py
pdm_rename-0.0.3.dist-info/entry_points.txt
pdm_rename-0.0.3.dist-info/WHEEL
pdm_rename-0.0.3.dist-info/METADATA
pdm_rename-0.0.3.dist-info/licenses/LICENSE
pdm_rename-0.0.3.dist-info/RECORD
