Metadata-Version: 2.1
Name: pdm-rename
Version: 0.0.3
Summary: Plugin, that allows to dynamically rename folders during the build stage.
License: MIT
Author-email: aleksul <me@aleksul.space>
Requires-Python: >=3.7
Requires-Dist: pdm<3.0,>=2.3.0
